dataframe_pointer/__init__.py
dataframe_pointer-0.0.2.dist-info/licenses/LICENSE
dataframe_pointer-0.0.2.dist-info/METADATA
dataframe_pointer-0.0.2.dist-info/WHEEL
dataframe_pointer-0.0.2.dist-info/top_level.txt
dataframe_pointer-0.0.2.dist-info/RECORD
