Metadata-Version: 2.4
Name: dataframe-pointer
Version: 0.0.2
Author: Hugo Dictus
Author-email: h.t.dictus@gmail.com
License: GNU GPL
Requires-Python: >=3.6
License-File: LICENSE
Requires-Dist: pandas
Dynamic: author
Dynamic: author-email
Dynamic: description
Dynamic: description-content-type
Dynamic: license
Dynamic: license-file
Dynamic: requires-dist
Dynamic: requires-python
